{
    "max_steps": 32,
    "panel_to_show": 2,
    "current_step": 1,
    "focus": {
        "row": 1,
        "column": 2
    },
    "last_step": 1,
    "steps": {
        "1": {
            "banks": {
                "1": {
                "clean": 0,
                "chan_mask": 1
                },
                "2": {
                "clean": 0,
                "chan_mask": 0
                }
            },
            "reference": 0,
            "duration": 30
        }
    },
    "num_plan_files": 1,
    "plan_filename": "test.pln",
    "plan_files": {
        "1": "test.pln"
    },
    "bank_names": {
        "1": {
            "name": "B1",
            "channels": {
                "1": "Channel 1",
                "2": "Channel 2",
                "3": "Ch. 3",
                "4": "Ch. 4",
                "5": "Ch. 5",
                "6": "Ch. 6",
                "7": "Ch. 7",
                "8": "Ch. 8"
            }
        },
        "2": {
            "name": "B1",
            "channels": {
                "1": "Channel 1",
                "2": "Channel 2",
                "3": "Ch. 3",
                "4": "Ch. 4",
                "5": "Ch. 5",
                "6": "Ch. 6",
                "7": "Ch. 7",
                "8": "Ch. 8"
            }
        },
        "3": {
            "name": "Bank 2",
            "channels": {
                "1": "Ch. 1",
                "2": "Ch. 2",
                "3": "Ch. 3",
                "4": "Ch. 4",
                "5": "Ch. 5",
                "6": "Ch. 6",
                "7": "Ch. 7",
                "8": "Ch. 8"
            }
        },
        "4": {
            "name": "Bank 3",
            "channels": {
                "1": "Ch. 1",
                "2": "Ch. 2",
                "3": "Ch. 3",
                "4": "Ch. 4",
                "5": "Ch. 5",
                "6": "Ch. 6",
                "7": "Ch. 7",
                "8": "Ch. 8"
            }
        }
    }
}